xmlpydict_parser.cp310-win_amd64.pyd
xmlpydict_parser-0.0.4.dist-info/LICENSE
xmlpydict_parser-0.0.4.dist-info/METADATA
xmlpydict_parser-0.0.4.dist-info/WHEEL
xmlpydict_parser-0.0.4.dist-info/top_level.txt
xmlpydict_parser-0.0.4.dist-info/RECORD
